MailClassification/LoadClassModel.py
MailClassification/LoadEmbeddsModel.py
MailClassification/LoadScalerModel.py
MailClassification/MailClassification.py
MailClassification/TextCleaner.py
MailClassification/WordReplacements.py
MailClassification/__init__.py
MailClassification-0.7.dist-info/METADATA
MailClassification-0.7.dist-info/WHEEL
MailClassification-0.7.dist-info/top_level.txt
MailClassification-0.7.dist-info/RECORD
