Metadata-Version: 2.1
Name: MailClassification
Version: 0.7
Summary: Classify Mail to Cargo or Tonnage
Home-page: UNKNOWN
Author: Ankit Mor
License: UNKNOWN
Platform: UNKNOWN
Requires-Dist: requests
Requires-Dist: beautifulSoup4
Requires-Dist: spacy >=3.7.2
Requires-Dist: torch ==2.1.2
Requires-Dist: tensorflow ==2.15.0
Requires-Dist: keras ==2.15.0
Requires-Dist: sentence-transformers ==2.3.1
Requires-Dist: joblib ==1.3.2
